altel_b2b_api/__init__.py
altel_b2b_api/api.py
altel_b2b_api/settings.py
altel_b2b_api-0.2.dist-info/licenses/LICENSE.md
altel_b2b_api-0.2.dist-info/METADATA
altel_b2b_api-0.2.dist-info/WHEEL
altel_b2b_api-0.2.dist-info/top_level.txt
altel_b2b_api-0.2.dist-info/RECORD
