Metadata-Version: 2.4
Name: altel_b2b_api
Version: 0.2
Summary: Библиотека предоставляет удобный интерфейс для взаимодействия с Altel B2B API
Home-page: https://github.com/litemat/altel_api
Download-URL: https://github.com/litemat/altel_api/archive/v0.2.zip
Author: @litemat
Author-email: legentea22@gmail.com
License: The MIT License (MIT), see LICENSE file
Classifier: Programming Language :: Python :: 3
Classifier: License :: OSI Approved :: MIT License
Classifier: Operating System :: OS Independent
License-File: LICENSE.md
Requires-Dist: setuptools>=80.9.0
Requires-Dist: dotenv>=0.9.9
Requires-Dist: python-dotenv>=1.1.0
Requires-Dist: cloudscraper>=1.2.71
Dynamic: author
Dynamic: author-email
Dynamic: classifier
Dynamic: description
Dynamic: description-content-type
Dynamic: download-url
Dynamic: home-page
Dynamic: license
Dynamic: license-file
Dynamic: requires-dist
Dynamic: summary
